pepperize_cdk_dynamodb_backup/__init__.py
pepperize_cdk_dynamodb_backup/py.typed
pepperize_cdk_dynamodb_backup/_jsii/__init__.py
pepperize_cdk_dynamodb_backup/_jsii/cdk-dynamodb-backup@0.0.485.jsii.tgz
pepperize_cdk_dynamodb_backup-0.0.485.dist-info/LICENSE
pepperize_cdk_dynamodb_backup-0.0.485.dist-info/METADATA
pepperize_cdk_dynamodb_backup-0.0.485.dist-info/WHEEL
pepperize_cdk_dynamodb_backup-0.0.485.dist-info/top_level.txt
pepperize_cdk_dynamodb_backup-0.0.485.dist-info/RECORD
