Metadata-Version: 2.1
Name: pepperize.cdk-dynamodb-backup
Version: 0.0.485
Summary: Backup and restore AWS DynamoDB Table to AWS S3 Bucket with AWS Data Pipeline.
Home-page: https://github.com/patrick.florek/cdk-dynamodb-backup.git
Author: Patrick Florek<patrick.florek@gmail.com>
License: MIT
Project-URL: Source, https://github.com/patrick.florek/cdk-dynamodb-backup.git
Classifier: Intended Audience :: Developers
Classifier: Operating System :: OS Independent
Classifier: Programming Language :: JavaScript
Classifier: Programming Language :: Python :: 3 :: Only
Classifier: Programming Language :: Python :: 3.9
Classifier: Programming Language :: Python :: 3.10
Classifier: Programming Language :: Python :: 3.11
Classifier: Typing :: Typed
Classifier: Development Status :: 5 - Production/Stable
Classifier: License :: OSI Approved
Requires-Python: ~=3.9
License-File: LICENSE
Requires-Dist: aws-cdk-lib<3.0.0,>=2.8.0
Requires-Dist: constructs<11.0.0,>=10.0.5
Requires-Dist: jsii<2.0.0,>=1.110.0
Requires-Dist: pepperize.cdk-private-bucket<0.0.305,>=0.0.304
Requires-Dist: publication>=0.0.3
Requires-Dist: typeguard<4.3.0,>=2.13.3
